punkz/__init__.py
punkz/core/__init__.py
punkz/core/cache/__init__.py
punkz/core/cache/cache.py
punkz/core/cache/providers/__init__.py
punkz/core/cache/providers/aws_s3_provider.py
punkz/core/cache/providers/local_provider.py
punkz/core/cache/providers/abstract/__init__.py
punkz/core/cache/providers/abstract/base_provider.py
punkz/core/processor/__init__.py
punkz/core/processor/processor.py
punkz/packages/__init__.py
punkz/packages/aws/__init__.py
punkz/packages/aws/aws.py
punkz/packages/aws/progress/__init__.py
punkz/packages/aws/progress/progress_percentage.py
punkz/packages/aws/s3/__init__.py
punkz/packages/aws/s3/s3.py
punkz/packages/fs_manager/__init__.py
punkz/packages/fs_manager/fs_manager.py
punkz/packages/log/__init__.py
punkz/packages/log/log.py
punkz-0.0.6.dist-info/LICENSE
punkz-0.0.6.dist-info/METADATA
punkz-0.0.6.dist-info/WHEEL
punkz-0.0.6.dist-info/top_level.txt
punkz-0.0.6.dist-info/RECORD
