Metadata-Version: 2.1
Name: punkz
Version: 0.0.6
Summary: Python utilities developed by Devpunks.
Author-email: Paolo Bianco <paolo.bianco@devpunks.com>
License: MIT
Classifier: Programming Language :: Python :: 3
Classifier: License :: OSI Approved :: MIT License
Classifier: Operating System :: OS Independent
Requires-Python: >=3.10
License-File: LICENSE
Requires-Dist: boto3 >=1.34
Requires-Dist: botocore >=1.34
